arcplot/__init__.py
arcplot/arcplot.py
arcplot-1.0.0.dist-info/LICENSE
arcplot-1.0.0.dist-info/METADATA
arcplot-1.0.0.dist-info/WHEEL
arcplot-1.0.0.dist-info/RECORD
