Metadata-Version: 2.3
Name: arcplot
Version: 1.0.0
Summary: arcplot is a library based on matplotlib for seamless creation of custom arc diagrams.
License: MIT
Author: Csaba Szallós Kis
Requires-Python: >=3.10,<4.0
Classifier: License :: OSI Approved :: MIT License
Classifier: Programming Language :: Python :: 3
Classifier: Programming Language :: Python :: 3.10
Classifier: Programming Language :: Python :: 3.11
Classifier: Programming Language :: Python :: 3.12
Classifier: Programming Language :: Python :: 3.13
Requires-Dist: PyQt5 (==5.15.11)
Requires-Dist: contourpy (==1.2.0)
Requires-Dist: cycler (==0.12.1)
Requires-Dist: fonttools (==4.48.1)
Requires-Dist: kiwisolver (==1.4.5)
Requires-Dist: matplotlib (==3.8.2)
Requires-Dist: numpy (==1.26.4)
Requires-Dist: packaging (==23.2)
Requires-Dist: pandas (==2.2.1)
Requires-Dist: pillow (==10.3.0)
Requires-Dist: pyparsing (==3.1.1)
Requires-Dist: python-dateutil (==2.8.2)
Requires-Dist: six (==1.16.0)
